README.md
setup.cfg
setup.py
Jellybeans.egg-info/PKG-INFO
Jellybeans.egg-info/SOURCES.txt
Jellybeans.egg-info/dependency_links.txt
Jellybeans.egg-info/requires.txt
Jellybeans.egg-info/top_level.txt
jellybeans/__init__.py
jellybeans.egg-info/PKG-INFO
jellybeans.egg-info/SOURCES.txt
jellybeans.egg-info/dependency_links.txt
jellybeans.egg-info/requires.txt
jellybeans.egg-info/top_level.txt
jellybeans/algos/__init__.py
jellybeans/algos/graphs/__init__.py
jellybeans/algos/graphs/funcs.py
jellybeans/algos/graphs/private_funcs.py
jellybeans/algos/sorts/__init__.py
jellybeans/algos/sorts/private_funcs.py
jellybeans/algos/sorts/sort.py
jellybeans/exceptions/__init__.py
jellybeans/exceptions/graph_property.py
jellybeans/exceptions/negative_cycle.py
jellybeans/exceptions/not_one_based_index.py
jellybeans/structures/__init__.py
jellybeans/structures/avl/__init__.py
jellybeans/structures/avl/avl.py
jellybeans/structures/avl/binary_node.py
jellybeans/structures/graph/__init__.py
jellybeans/structures/graph/graph.py
jellybeans/structures/graph/private_funcs.py
jellybeans/structures/heaps/__init__.py
jellybeans/structures/heaps/priority_queue.py
jellybeans/structures/linkedLists/__init__.py
jellybeans/structures/linkedLists/doubly_linked_list.py
jellybeans/structures/linkedLists/doubly_node.py
jellybeans/structures/linkedLists/linked_list.py
jellybeans/structures/linkedLists/node.py
jellybeans/structures/linkedLists/tail_linked_list.py
jellybeans/structures/queue/__init__.py
jellybeans/structures/queue/deque.py
jellybeans/structures/queue/queue.py
jellybeans/structures/stack/__init__.py
jellybeans/structures/stack/stack.py
jellybeans/structures/ufds/__init__.py
jellybeans/structures/ufds/ufds.py
jellybeans/visualiser/Animate.py
jellybeans/visualiser/__init__.py