Metadata-Version: 2.1
Name: Jellybeans
Version: 1.0.4
Summary: A Data Structure Package
Home-page: https://github.com/Jcheez/jellybeans
Author: Lee Jia Jun
Author-email: jiajunlee2@gmail.com
License: MIT
Keywords: Data-Structures
Platform: UNKNOWN
Classifier: Programming Language :: Python :: 3
Classifier: License :: OSI Approved :: MIT License
Classifier: Operating System :: OS Independent
Requires-Python: >=3.7
